ims_envista/__init__.py
ims_envista/commons.py
ims_envista/const.py
ims_envista/ims_envista.py
ims_envista/ims_variable.py
ims_envista/meteo_data.py
ims_envista/station_data.py
ims_envista/version.py
tests/__init__.py
tests/unit/__init__.py
tests/unit/test_ims_envista.py
tests/unit/test_version.py
ims_envista-0.1.13.dist-info/LICENSE
ims_envista-0.1.13.dist-info/METADATA
ims_envista-0.1.13.dist-info/WHEEL
ims_envista-0.1.13.dist-info/top_level.txt
ims_envista-0.1.13.dist-info/RECORD
